[
    {
        "TEAM": "NYK",
        "HOME": false,
        "RECORD": "47-26",
        "STATS": {
            "BASIC": {
                "Starters": "Totals",
                "MP": "240",
                "FG": "37",
                "FGA": "71",
                "FG%": ".521",
                "3P": "14",
                "3PA": "27",
                "3P%": ".519",
                "FT": "14",
                "FTA": "20",
                "FT%": ".700",
                "ORB": "6",
                "DRB": "18",
                "TRB": "24",
                "AST": "17",
                "STL": "8",
                "BLK": "3",
                "TOV": "13",
                "PF": "25",
                "PTS": "102",
                "+/-": ""
            },
            "ADVANCE": {
                "Starters": "Totals",
                "MP": "240",
                "TS%": ".639",
                "eFG%": ".620",
                "3PAr": ".380",
                "FTr": ".282",
                "ORB%": "19.4",
                "DRB%": "72.0",
                "TRB%": "42.9",
                "AST%": "45.9",
                "STL%": "9.7",
                "BLK%": "7.5",
                "TOV%": "14.0",
                "USG%": "100.0",
                "ORtg": "123.1",
                "DRtg": "108.6"
            }
        }
    },
    {
        "TEAM": "MIA",
        "HOME": true,
        "RECORD": "58-16",
        "STATS": {
            "BASIC": {
                "Starters": "Totals",
                "MP": "240",
                "FG": "30",
                "FGA": "60",
                "FG%": ".500",
                "3P": "8",
                "3PA": "20",
                "3P%": ".400",
                "FT": "22",
                "FTA": "27",
                "FT%": ".815",
                "ORB": "7",
                "DRB": "25",
                "TRB": "32",
                "AST": "18",
                "STL": "7",
                "BLK": "3",
                "TOV": "19",
                "PF": "19",
                "PTS": "90",
                "+/-": ""
            },
            "ADVANCE": {
                "Starters": "Totals",
                "MP": "240",
                "TS%": ".626",
                "eFG%": ".567",
                "3PAr": ".333",
                "FTr": ".450",
                "ORB%": "28.0",
                "DRB%": "80.6",
                "TRB%": "57.1",
                "AST%": "60.0",
                "STL%": "8.4",
                "BLK%": "6.8",
                "TOV%": "20.9",
                "USG%": "100.0",
                "ORtg": "108.6",
                "DRtg": "123.1"
            }
        }
    }
]