[
    {
        "TEAM": "LAL",
        "HOME": false,
        "RECORD": "38-16",
        "STATS": {
            "BASIC": {
                "Starters": "Totals",
                "MP": "240",
                "FG": "42",
                "FGA": "87",
                "FG%": ".483",
                "3P": "9",
                "3PA": "19",
                "3P%": ".474",
                "FT": "14",
                "FTA": "19",
                "FT%": ".737",
                "ORB": "17",
                "DRB": "31",
                "TRB": "48",
                "AST": "21",
                "STL": "11",
                "BLK": "3",
                "TOV": "11",
                "PF": "22",
                "PTS": "107",
                "+/-": ""
            },
            "ADVANCE": {
                "Starters": "Totals",
                "MP": "240",
                "TS%": ".561",
                "eFG%": ".534",
                "3PAr": ".218",
                "FTr": ".218",
                "ORB%": "39.5",
                "DRB%": "66.0",
                "TRB%": "53.3",
                "AST%": "50.0",
                "STL%": "12.6",
                "BLK%": "4.7",
                "TOV%": "10.3",
                "USG%": "100.0",
                "ORtg": "122.1",
                "DRtg": "103.8"
            }
        }
    },
    {
        "TEAM": "NYK",
        "HOME": true,
        "RECORD": "20-34",
        "STATS": {
            "BASIC": {
                "Starters": "Totals",
                "MP": "240",
                "FG": "37",
                "FGA": "85",
                "FG%": ".435",
                "3P": "5",
                "3PA": "21",
                "3P%": ".238",
                "FT": "12",
                "FTA": "18",
                "FT%": ".667",
                "ORB": "16",
                "DRB": "26",
                "TRB": "42",
                "AST": "19",
                "STL": "7",
                "BLK": "3",
                "TOV": "14",
                "PF": "20",
                "PTS": "91",
                "+/-": ""
            },
            "ADVANCE": {
                "Starters": "Totals",
                "MP": "240",
                "TS%": ".490",
                "eFG%": ".465",
                "3PAr": ".247",
                "FTr": ".212",
                "ORB%": "34.0",
                "DRB%": "60.5",
                "TRB%": "46.7",
                "AST%": "51.4",
                "STL%": "8.0",
                "BLK%": "4.4",
                "TOV%": "13.1",
                "USG%": "100.0",
                "ORtg": "103.8",
                "DRtg": "122.1"
            }
        }
    }
]