[
    {
        "TEAM": "BOS",
        "HOME": false,
        "RECORD": "35-8",
        "STATS": {
            "BASIC": {
                "Starters": "Totals",
                "MP": "240",
                "FG": "43",
                "FGA": "97",
                "FG%": ".443",
                "3P": "1",
                "3PA": "5",
                "3P%": ".200",
                "FT": "10",
                "FTA": "13",
                "FT%": ".769",
                "ORB": "14",
                "DRB": "38",
                "TRB": "52",
                "AST": "31",
                "STL": "7",
                "BLK": "13",
                "TOV": "12",
                "PF": "16",
                "PTS": "97"
            },
            "ADVANCE": {
                "Starters": "Totals",
                "MP": "240",
                "TS%": ".472",
                "eFG%": ".448",
                "3PAr": ".052",
                "FTr": ".134",
                "ORB%": "30.4",
                "DRB%": "74.5",
                "TRB%": "53.6",
                "AST%": "72.1",
                "STL%": "7.4",
                "BLK%": "15.9",
                "TOV%": "10.5",
                "USG%": "100.0",
                "ORtg": "102.0",
                "DRtg": "92.6"
            }
        }
    },
    {
        "TEAM": "WSB",
        "HOME": true,
        "RECORD": "23-23",
        "STATS": {
            "BASIC": {
                "Starters": "Totals",
                "MP": "240",
                "FG": "35",
                "FGA": "86",
                "FG%": ".407",
                "3P": "3",
                "3PA": "4",
                "3P%": ".750",
                "FT": "15",
                "FTA": "21",
                "FT%": ".714",
                "ORB": "13",
                "DRB": "32",
                "TRB": "45",
                "AST": "16",
                "STL": "6",
                "BLK": "12",
                "TOV": "13",
                "PF": "16",
                "PTS": "88"
            },
            "ADVANCE": {
                "Starters": "Totals",
                "MP": "240",
                "TS%": ".462",
                "eFG%": ".424",
                "3PAr": ".047",
                "FTr": ".244",
                "ORB%": "25.5",
                "DRB%": "69.6",
                "TRB%": "46.4",
                "AST%": "45.7",
                "STL%": "6.3",
                "BLK%": "13.0",
                "TOV%": "12.0",
                "USG%": "100.0",
                "ORtg": "92.6",
                "DRtg": "102.0"
            }
        }
    }
]