[
    {
        "TEAM": "LAL",
        "HOME": false,
        "RECORD": "33-8",
        "STATS": {
            "BASIC": {
                "Starters": "Totals",
                "MP": "240",
                "FG": "43",
                "FGA": "86",
                "FG%": ".500",
                "3P": "5",
                "3PA": "21",
                "3P%": ".238",
                "FT": "17",
                "FTA": "23",
                "FT%": ".739",
                "ORB": "17",
                "DRB": "29",
                "TRB": "46",
                "AST": "25",
                "STL": "5",
                "BLK": "9",
                "TOV": "13",
                "PF": "16",
                "PTS": "108",
                "+/-": ""
            },
            "ADVANCE": {
                "Starters": "Totals",
                "MP": "240",
                "TS%": ".562",
                "eFG%": ".529",
                "3PAr": ".244",
                "FTr": ".267",
                "ORB%": "48.6",
                "DRB%": "78.4",
                "TRB%": "63.9",
                "AST%": "58.1",
                "STL%": "5.8",
                "BLK%": "14.1",
                "TOV%": "11.9",
                "USG%": "100.0",
                "ORtg": "126.0",
                "DRtg": "113.2"
            }
        }
    },
    {
        "TEAM": "LAC",
        "HOME": true,
        "RECORD": "9-32",
        "STATS": {
            "BASIC": {
                "Starters": "Totals",
                "MP": "240",
                "FG": "38",
                "FGA": "78",
                "FG%": ".487",
                "3P": "6",
                "3PA": "14",
                "3P%": ".429",
                "FT": "15",
                "FTA": "17",
                "FT%": ".882",
                "ORB": "8",
                "DRB": "18",
                "TRB": "26",
                "AST": "20",
                "STL": "7",
                "BLK": "5",
                "TOV": "10",
                "PF": "16",
                "PTS": "97",
                "+/-": ""
            },
            "ADVANCE": {
                "Starters": "Totals",
                "MP": "240",
                "TS%": ".567",
                "eFG%": ".526",
                "3PAr": ".179",
                "FTr": ".218",
                "ORB%": "21.6",
                "DRB%": "51.4",
                "TRB%": "36.1",
                "AST%": "52.6",
                "STL%": "8.2",
                "BLK%": "7.7",
                "TOV%": "10.5",
                "USG%": "100.0",
                "ORtg": "113.2",
                "DRtg": "126.0"
            }
        }
    }
]