[
    {
        "TEAM": "LAL",
        "HOME": false,
        "RECORD": "41-9",
        "STATS": {
            "BASIC": {
                "Starters": "Totals",
                "MP": "240",
                "FG": "43",
                "FGA": "88",
                "FG%": ".489",
                "3P": "3",
                "3PA": "20",
                "3P%": ".150",
                "FT": "12",
                "FTA": "16",
                "FT%": ".750",
                "ORB": "12",
                "DRB": "30",
                "TRB": "42",
                "AST": "25",
                "STL": "7",
                "BLK": "5",
                "TOV": "6",
                "PF": "16",
                "PTS": "101",
                "+/-": ""
            },
            "ADVANCE": {
                "Starters": "Totals",
                "MP": "240",
                "TS%": ".531",
                "eFG%": ".506",
                "3PAr": ".227",
                "FTr": ".182",
                "ORB%": "30.8",
                "DRB%": "66.7",
                "TRB%": "50.0",
                "AST%": "58.1",
                "STL%": "8.2",
                "BLK%": "7.8",
                "TOV%": "5.9",
                "USG%": "100.0",
                "ORtg": "118.6",
                "DRtg": "106.9"
            }
        }
    },
    {
        "TEAM": "CLE",
        "HOME": true,
        "RECORD": "39-10",
        "STATS": {
            "BASIC": {
                "Starters": "Totals",
                "MP": "240",
                "FG": "34",
                "FGA": "87",
                "FG%": ".391",
                "3P": "11",
                "3PA": "23",
                "3P%": ".478",
                "FT": "12",
                "FTA": "19",
                "FT%": ".632",
                "ORB": "15",
                "DRB": "27",
                "TRB": "42",
                "AST": "22",
                "STL": "5",
                "BLK": "4",
                "TOV": "9",
                "PF": "21",
                "PTS": "91",
                "+/-": ""
            },
            "ADVANCE": {
                "Starters": "Totals",
                "MP": "240",
                "TS%": ".477",
                "eFG%": ".454",
                "3PAr": ".264",
                "FTr": ".218",
                "ORB%": "33.3",
                "DRB%": "69.2",
                "TRB%": "50.0",
                "AST%": "64.7",
                "STL%": "5.9",
                "BLK%": "5.9",
                "TOV%": "8.6",
                "USG%": "100.0",
                "ORtg": "106.9",
                "DRtg": "118.6"
            }
        }
    }
]