[
    {
        "TEAM": "LAL",
        "HOME": false,
        "RECORD": "42-13",
        "STATS": {
            "BASIC": {
                "Starters": "Totals",
                "MP": "240",
                "FG": "33",
                "FGA": "76",
                "FG%": ".434",
                "3P": "3",
                "3PA": "4",
                "3P%": ".750",
                "FT": "28",
                "FTA": "34",
                "FT%": ".824",
                "ORB": "15",
                "DRB": "32",
                "TRB": "47",
                "AST": "19",
                "STL": "8",
                "BLK": "7",
                "TOV": "13",
                "PF": "22",
                "PTS": "97"
            },
            "ADVANCE": {
                "Starters": "Totals",
                "MP": "240",
                "TS%": ".533",
                "eFG%": ".454",
                "3PAr": ".053",
                "FTr": ".447",
                "ORB%": "31.3",
                "DRB%": "66.7",
                "TRB%": "49.0",
                "AST%": "57.6",
                "STL%": "8.9",
                "BLK%": "8.6",
                "TOV%": "12.5",
                "USG%": "100.0",
                "ORtg": "107.4",
                "DRtg": "103.0"
            }
        }
    },
    {
        "TEAM": "PHO",
        "HOME": true,
        "RECORD": "22-33",
        "STATS": {
            "BASIC": {
                "Starters": "Totals",
                "MP": "240",
                "FG": "37",
                "FGA": "87",
                "FG%": ".425",
                "3P": "3",
                "3PA": "6",
                "3P%": ".500",
                "FT": "16",
                "FTA": "18",
                "FT%": ".889",
                "ORB": "16",
                "DRB": "33",
                "TRB": "49",
                "AST": "25",
                "STL": "5",
                "BLK": "7",
                "TOV": "16",
                "PF": "28",
                "PTS": "93"
            },
            "ADVANCE": {
                "Starters": "Totals",
                "MP": "240",
                "TS%": ".490",
                "eFG%": ".443",
                "3PAr": ".069",
                "FTr": ".207",
                "ORB%": "33.3",
                "DRB%": "68.8",
                "TRB%": "51.0",
                "AST%": "67.6",
                "STL%": "5.5",
                "BLK%": "9.7",
                "TOV%": "14.4",
                "USG%": "100.0",
                "ORtg": "103.0",
                "DRtg": "107.4"
            }
        }
    }
]