[
    {
        "TEAM": "HOU",
        "HOME": false,
        "RECORD": "19-11",
        "STATS": {
            "BASIC": {
                "Starters": "Totals",
                "MP": "240",
                "FG": "45",
                "FGA": "86",
                "FG%": ".523",
                "3P": "12",
                "3PA": "24",
                "3P%": ".500",
                "FT": "9",
                "FTA": "18",
                "FT%": ".500",
                "ORB": "11",
                "DRB": "39",
                "TRB": "50",
                "AST": "28",
                "STL": "3",
                "BLK": "9",
                "TOV": "10",
                "PF": "16",
                "PTS": "111",
                "+/-": ""
            },
            "ADVANCE": {
                "Starters": "Totals",
                "MP": "240",
                "TS%": ".591",
                "eFG%": ".593",
                "3PAr": ".279",
                "FTr": ".209",
                "ORB%": "25.6",
                "DRB%": "73.6",
                "TRB%": "52.1",
                "AST%": "62.2",
                "STL%": "3.2",
                "BLK%": "12.7",
                "TOV%": "9.6",
                "USG%": "100.0",
                "ORtg": "119.4",
                "DRtg": "105.4"
            }
        }
    },
    {
        "TEAM": "SAS",
        "HOME": true,
        "RECORD": "22-7",
        "STATS": {
            "BASIC": {
                "Starters": "Totals",
                "MP": "240",
                "FG": "37",
                "FGA": "91",
                "FG%": ".407",
                "3P": "5",
                "3PA": "20",
                "3P%": ".250",
                "FT": "19",
                "FTA": "23",
                "FT%": ".826",
                "ORB": "14",
                "DRB": "32",
                "TRB": "46",
                "AST": "18",
                "STL": "6",
                "BLK": "9",
                "TOV": "9",
                "PF": "13",
                "PTS": "98",
                "+/-": ""
            },
            "ADVANCE": {
                "Starters": "Totals",
                "MP": "240",
                "TS%": ".485",
                "eFG%": ".434",
                "3PAr": ".220",
                "FTr": ".253",
                "ORB%": "26.4",
                "DRB%": "74.4",
                "TRB%": "47.9",
                "AST%": "48.6",
                "STL%": "6.5",
                "BLK%": "14.5",
                "TOV%": "8.2",
                "USG%": "100.0",
                "ORtg": "105.4",
                "DRtg": "119.4"
            }
        }
    }
]