[
    {
        "TEAM": "SAS",
        "HOME": false,
        "RECORD": "58-16",
        "STATS": {
            "BASIC": {
                "Starters": "Totals",
                "MP": "240",
                "FG": "37",
                "FGA": "80",
                "FG%": ".463",
                "3P": "8",
                "3PA": "17",
                "3P%": ".471",
                "FT": "21",
                "FTA": "25",
                "FT%": ".840",
                "ORB": "15",
                "DRB": "25",
                "TRB": "40",
                "AST": "18",
                "STL": "10",
                "BLK": "5",
                "TOV": "8",
                "PF": "19",
                "PTS": "103",
                "+/-": ""
            },
            "ADVANCE": {
                "Starters": "Totals",
                "MP": "240",
                "TS%": ".566",
                "eFG%": ".513",
                "3PAr": ".213",
                "FTr": ".313",
                "ORB%": "35.7",
                "DRB%": "78.1",
                "TRB%": "54.1",
                "AST%": "48.6",
                "STL%": "12.1",
                "BLK%": "9.1",
                "TOV%": "8.1",
                "USG%": "100.0",
                "ORtg": "124.8",
                "DRtg": "93.3"
            }
        }
    },
    {
        "TEAM": "IND",
        "HOME": true,
        "RECORD": "52-23",
        "STATS": {
            "BASIC": {
                "Starters": "Totals",
                "MP": "240",
                "FG": "26",
                "FGA": "69",
                "FG%": ".377",
                "3P": "6",
                "3PA": "14",
                "3P%": ".429",
                "FT": "19",
                "FTA": "24",
                "FT%": ".792",
                "ORB": "7",
                "DRB": "27",
                "TRB": "34",
                "AST": "14",
                "STL": "4",
                "BLK": "3",
                "TOV": "15",
                "PF": "22",
                "PTS": "77",
                "+/-": ""
            },
            "ADVANCE": {
                "Starters": "Totals",
                "MP": "240",
                "TS%": ".484",
                "eFG%": ".420",
                "3PAr": ".203",
                "FTr": ".348",
                "ORB%": "21.9",
                "DRB%": "64.3",
                "TRB%": "45.9",
                "AST%": "53.8",
                "STL%": "4.8",
                "BLK%": "4.8",
                "TOV%": "15.9",
                "USG%": "100.0",
                "ORtg": "93.3",
                "DRtg": "124.8"
            }
        }
    }
]