[
    {
        "TEAM": "ATL",
        "HOME": false,
        "RECORD": "30-18",
        "STATS": {
            "BASIC": {
                "Starters": "Totals",
                "MP": "240",
                "FG": "35",
                "FGA": "76",
                "FG%": ".461",
                "3P": "4",
                "3PA": "20",
                "3P%": ".200",
                "FT": "17",
                "FTA": "22",
                "FT%": ".773",
                "ORB": "9",
                "DRB": "29",
                "TRB": "38",
                "AST": "20",
                "STL": "8",
                "BLK": "2",
                "TOV": "12",
                "PF": "22",
                "PTS": "91",
                "+/-": ""
            },
            "ADVANCE": {
                "Starters": "Totals",
                "MP": "240",
                "TS%": ".531",
                "eFG%": ".487",
                "3PAr": ".263",
                "FTr": ".289",
                "ORB%": "21.4",
                "DRB%": "78.4",
                "TRB%": "48.1",
                "AST%": "57.1",
                "STL%": "9.1",
                "BLK%": "3.8",
                "TOV%": "12.3",
                "USG%": "100.0",
                "ORtg": "103.6",
                "DRtg": "116.1"
            }
        }
    },
    {
        "TEAM": "DAL",
        "HOME": true,
        "RECORD": "31-15",
        "STATS": {
            "BASIC": {
                "Starters": "Totals",
                "MP": "240",
                "FG": "36",
                "FGA": "73",
                "FG%": ".493",
                "3P": "8",
                "3PA": "21",
                "3P%": ".381",
                "FT": "22",
                "FTA": "27",
                "FT%": ".815",
                "ORB": "8",
                "DRB": "33",
                "TRB": "41",
                "AST": "28",
                "STL": "6",
                "BLK": "4",
                "TOV": "13",
                "PF": "17",
                "PTS": "102",
                "+/-": ""
            },
            "ADVANCE": {
                "Starters": "Totals",
                "MP": "240",
                "TS%": ".601",
                "eFG%": ".548",
                "3PAr": ".288",
                "FTr": ".370",
                "ORB%": "21.6",
                "DRB%": "78.6",
                "TRB%": "51.9",
                "AST%": "77.8",
                "STL%": "6.8",
                "BLK%": "7.1",
                "TOV%": "13.3",
                "USG%": "100.0",
                "ORtg": "116.1",
                "DRtg": "103.6"
            }
        }
    }
]