[
    {
        "TEAM": "DAL",
        "HOME": false,
        "RECORD": "47-20",
        "STATS": {
            "BASIC": {
                "Starters": "Totals",
                "MP": "240",
                "FG": "40",
                "FGA": "67",
                "FG%": ".597",
                "3P": "9",
                "3PA": "21",
                "3P%": ".429",
                "FT": "12",
                "FTA": "13",
                "FT%": ".923",
                "ORB": "6",
                "DRB": "27",
                "TRB": "33",
                "AST": "30",
                "STL": "5",
                "BLK": "4",
                "TOV": "15",
                "PF": "17",
                "PTS": "101",
                "+/-": ""
            },
            "ADVANCE": {
                "Starters": "Totals",
                "MP": "240",
                "TS%": ".694",
                "eFG%": ".664",
                "3PAr": ".313",
                "FTr": ".194",
                "ORB%": "24.0",
                "DRB%": "64.3",
                "TRB%": "49.3",
                "AST%": "75.0",
                "STL%": "6.1",
                "BLK%": "5.6",
                "TOV%": "17.1",
                "USG%": "100.0",
                "ORtg": "123.0",
                "DRtg": "126.6"
            }
        }
    },
    {
        "TEAM": "POR",
        "HOME": true,
        "RECORD": "38-29",
        "STATS": {
            "BASIC": {
                "Starters": "Totals",
                "MP": "240",
                "FG": "40",
                "FGA": "85",
                "FG%": ".471",
                "3P": "6",
                "3PA": "14",
                "3P%": ".429",
                "FT": "18",
                "FTA": "23",
                "FT%": ".783",
                "ORB": "15",
                "DRB": "19",
                "TRB": "34",
                "AST": "19",
                "STL": "8",
                "BLK": "5",
                "TOV": "7",
                "PF": "15",
                "PTS": "104",
                "+/-": ""
            },
            "ADVANCE": {
                "Starters": "Totals",
                "MP": "240",
                "TS%": ".547",
                "eFG%": ".506",
                "3PAr": ".165",
                "FTr": ".271",
                "ORB%": "35.7",
                "DRB%": "76.0",
                "TRB%": "50.7",
                "AST%": "47.5",
                "STL%": "9.7",
                "BLK%": "10.9",
                "TOV%": "6.9",
                "USG%": "100.0",
                "ORtg": "126.6",
                "DRtg": "123.0"
            }
        }
    }
]