[
    {
        "TEAM": "CHI",
        "HOME": false,
        "RECORD": "12-0",
        "STATS": {
            "BASIC": {
                "Starters": "Totals",
                "MP": "240",
                "FG": "40",
                "FGA": "81",
                "FG%": ".494",
                "3P": "2",
                "3PA": "11",
                "3P%": ".182",
                "FT": "28",
                "FTA": "47",
                "FT%": ".596",
                "ORB": "15",
                "DRB": "31",
                "TRB": "46",
                "AST": "21",
                "STL": "8",
                "BLK": "6",
                "TOV": "14",
                "PF": "25",
                "PTS": "110"
            },
            "ADVANCE": {
                "Starters": "Totals",
                "MP": "240",
                "TS%": ".541",
                "eFG%": ".506",
                "3PAr": ".136",
                "FTr": ".580",
                "ORB%": "31.9",
                "DRB%": "66.0",
                "TRB%": "48.9",
                "AST%": "52.5",
                "STL%": "8.2",
                "BLK%": "9.0",
                "TOV%": "12.1",
                "USG%": "100.0",
                "ORtg": "112.9",
                "DRtg": "94.4"
            }
        }
    },
    {
        "TEAM": "DEN",
        "HOME": true,
        "RECORD": "4-8",
        "STATS": {
            "BASIC": {
                "Starters": "Totals",
                "MP": "240",
                "FG": "30",
                "FGA": "87",
                "FG%": ".345",
                "3P": "6",
                "3PA": "20",
                "3P%": ".300",
                "FT": "26",
                "FTA": "32",
                "FT%": ".813",
                "ORB": "16",
                "DRB": "32",
                "TRB": "48",
                "AST": "20",
                "STL": "11",
                "BLK": "5",
                "TOV": "16",
                "PF": "34",
                "PTS": "92"
            },
            "ADVANCE": {
                "Starters": "Totals",
                "MP": "240",
                "TS%": ".455",
                "eFG%": ".379",
                "3PAr": ".230",
                "FTr": ".368",
                "ORB%": "34.0",
                "DRB%": "68.1",
                "TRB%": "51.1",
                "AST%": "66.7",
                "STL%": "11.3",
                "BLK%": "7.1",
                "TOV%": "13.7",
                "USG%": "100.0",
                "ORtg": "94.4",
                "DRtg": "112.9"
            }
        }
    }
]