[
    {
        "TEAM": "ORL",
        "HOME": false,
        "RECORD": "11-17",
        "STATS": {
            "BASIC": {
                "Starters": "Totals",
                "MP": "240",
                "FG": "37",
                "FGA": "86",
                "FG%": ".430",
                "3P": "6",
                "3PA": "18",
                "3P%": ".333",
                "FT": "9",
                "FTA": "14",
                "FT%": ".643",
                "ORB": "12",
                "DRB": "17",
                "TRB": "29",
                "AST": "19",
                "STL": "7",
                "BLK": "1",
                "TOV": "10",
                "PF": "21",
                "PTS": "89"
            },
            "ADVANCE": {
                "Starters": "Totals",
                "MP": "240",
                "TS%": ".483",
                "eFG%": ".465",
                "3PAr": ".209",
                "FTr": ".163",
                "ORB%": "26.7",
                "DRB%": "47.2",
                "TRB%": "35.8",
                "AST%": "51.4",
                "STL%": "8.2",
                "BLK%": "1.4",
                "TOV%": "9.8",
                "USG%": "100.0",
                "ORtg": "104.6",
                "DRtg": "129.3"
            }
        }
    },
    {
        "TEAM": "CHI",
        "HOME": true,
        "RECORD": "28-4",
        "STATS": {
            "BASIC": {
                "Starters": "Totals",
                "MP": "240",
                "FG": "44",
                "FGA": "82",
                "FG%": ".537",
                "3P": "3",
                "3PA": "11",
                "3P%": ".273",
                "FT": "19",
                "FTA": "25",
                "FT%": ".760",
                "ORB": "19",
                "DRB": "33",
                "TRB": "52",
                "AST": "30",
                "STL": "9",
                "BLK": "3",
                "TOV": "12",
                "PF": "15",
                "PTS": "110"
            },
            "ADVANCE": {
                "Starters": "Totals",
                "MP": "240",
                "TS%": ".591",
                "eFG%": ".555",
                "3PAr": ".134",
                "FTr": ".305",
                "ORB%": "52.8",
                "DRB%": "73.3",
                "TRB%": "64.2",
                "AST%": "68.2",
                "STL%": "10.6",
                "BLK%": "4.4",
                "TOV%": "11.4",
                "USG%": "100.0",
                "ORtg": "129.3",
                "DRtg": "104.6"
            }
        }
    }
]