[
    {
        "TEAM": "DET",
        "HOME": false,
        "RECORD": "48-20",
        "STATS": {
            "BASIC": {
                "Starters": "Totals",
                "MP": "240",
                "FG": "29",
                "FGA": "76",
                "FG%": ".382",
                "3P": "4",
                "3PA": "14",
                "3P%": ".286",
                "FT": "26",
                "FTA": "39",
                "FT%": ".667",
                "ORB": "9",
                "DRB": "24",
                "TRB": "33",
                "AST": "15",
                "STL": "11",
                "BLK": "2",
                "TOV": "9",
                "PF": "18",
                "PTS": "88"
            },
            "ADVANCE": {
                "Starters": "Totals",
                "MP": "240",
                "TS%": ".472",
                "eFG%": ".408",
                "3PAr": ".184",
                "FTr": ".513",
                "ORB%": "18.0",
                "DRB%": "60.0",
                "TRB%": "36.7",
                "AST%": "51.7",
                "STL%": "12.2",
                "BLK%": "3.2",
                "TOV%": "8.8",
                "USG%": "100.0",
                "ORtg": "97.8",
                "DRtg": "114.5"
            }
        }
    },
    {
        "TEAM": "CHI",
        "HOME": true,
        "RECORD": "59-9",
        "STATS": {
            "BASIC": {
                "Starters": "Totals",
                "MP": "240",
                "FG": "40",
                "FGA": "85",
                "FG%": ".471",
                "3P": "7",
                "3PA": "23",
                "3P%": ".304",
                "FT": "16",
                "FTA": "19",
                "FT%": ".842",
                "ORB": "16",
                "DRB": "41",
                "TRB": "57",
                "AST": "30",
                "STL": "5",
                "BLK": "1",
                "TOV": "15",
                "PF": "26",
                "PTS": "103"
            },
            "ADVANCE": {
                "Starters": "Totals",
                "MP": "240",
                "TS%": ".552",
                "eFG%": ".512",
                "3PAr": ".271",
                "FTr": ".224",
                "ORB%": "40.0",
                "DRB%": "82.0",
                "TRB%": "63.3",
                "AST%": "75.0",
                "STL%": "5.6",
                "BLK%": "1.6",
                "TOV%": "13.8",
                "USG%": "100.0",
                "ORtg": "114.5",
                "DRtg": "97.8"
            }
        }
    }
]