[
    {
        "TEAM": "CLE",
        "HOME": false,
        "RECORD": "8-1",
        "STATS": {
            "BASIC": {
                "Starters": "Totals",
                "MP": "240",
                "FG": "33",
                "FGA": "78",
                "FG%": ".423",
                "3P": "6",
                "3PA": "28",
                "3P%": ".214",
                "FT": "18",
                "FTA": "31",
                "FT%": ".581",
                "ORB": "12",
                "DRB": "37",
                "TRB": "49",
                "AST": "12",
                "STL": "6",
                "BLK": "1",
                "TOV": "12",
                "PF": "19",
                "PTS": "90",
                "+/-": ""
            },
            "ADVANCE": {
                "Starters": "Totals",
                "MP": "240",
                "TS%": ".491",
                "eFG%": ".462",
                "3PAr": ".359",
                "FTr": ".397",
                "ORB%": "25.0",
                "DRB%": "78.7",
                "TRB%": "51.6",
                "AST%": "36.4",
                "STL%": "6.7",
                "BLK%": "1.9",
                "TOV%": "11.6",
                "USG%": "100.0",
                "ORtg": "99.8",
                "DRtg": "93.1"
            }
        }
    },
    {
        "TEAM": "NYK",
        "HOME": true,
        "RECORD": "4-6",
        "STATS": {
            "BASIC": {
                "Starters": "Totals",
                "MP": "240",
                "FG": "29",
                "FGA": "79",
                "FG%": ".367",
                "3P": "9",
                "3PA": "27",
                "3P%": ".333",
                "FT": "17",
                "FTA": "21",
                "FT%": ".810",
                "ORB": "10",
                "DRB": "36",
                "TRB": "46",
                "AST": "16",
                "STL": "7",
                "BLK": "4",
                "TOV": "14",
                "PF": "26",
                "PTS": "84",
                "+/-": ""
            },
            "ADVANCE": {
                "Starters": "Totals",
                "MP": "240",
                "TS%": ".476",
                "eFG%": ".424",
                "3PAr": ".342",
                "FTr": ".266",
                "ORB%": "21.3",
                "DRB%": "75.0",
                "TRB%": "48.4",
                "AST%": "55.2",
                "STL%": "7.8",
                "BLK%": "8.0",
                "TOV%": "13.7",
                "USG%": "100.0",
                "ORtg": "93.1",
                "DRtg": "99.8"
            }
        }
    }
]