[
    {
        "TEAM": "NYK",
        "HOME": false,
        "RECORD": "4-10",
        "STATS": {
            "BASIC": {
                "Starters": "Totals",
                "MP": "240",
                "FG": "23",
                "FGA": "76",
                "FG%": ".303",
                "3P": "2",
                "3PA": "10",
                "3P%": ".200",
                "FT": "11",
                "FTA": "17",
                "FT%": ".647",
                "ORB": "7",
                "DRB": "28",
                "TRB": "35",
                "AST": "12",
                "STL": "3",
                "BLK": "6",
                "TOV": "14",
                "PF": "22",
                "PTS": "59",
                "+/-": ""
            },
            "ADVANCE": {
                "Starters": "Totals",
                "MP": "240",
                "TS%": ".353",
                "eFG%": ".316",
                "3PAr": ".132",
                "FTr": ".224",
                "ORB%": "14.9",
                "DRB%": "71.8",
                "TRB%": "40.7",
                "AST%": "52.2",
                "STL%": "3.5",
                "BLK%": "10.5",
                "TOV%": "14.4",
                "USG%": "100.0",
                "ORtg": "69.1",
                "DRtg": "121.9"
            }
        }
    },
    {
        "TEAM": "BOS",
        "HOME": true,
        "RECORD": "12-2",
        "STATS": {
            "BASIC": {
                "Starters": "Totals",
                "MP": "240",
                "FG": "37",
                "FGA": "79",
                "FG%": ".468",
                "3P": "12",
                "3PA": "22",
                "3P%": ".545",
                "FT": "18",
                "FTA": "25",
                "FT%": ".720",
                "ORB": "11",
                "DRB": "40",
                "TRB": "51",
                "AST": "27",
                "STL": "7",
                "BLK": "6",
                "TOV": "6",
                "PF": "24",
                "PTS": "104",
                "+/-": ""
            },
            "ADVANCE": {
                "Starters": "Totals",
                "MP": "240",
                "TS%": ".578",
                "eFG%": ".544",
                "3PAr": ".278",
                "FTr": ".316",
                "ORB%": "28.2",
                "DRB%": "85.1",
                "TRB%": "59.3",
                "AST%": "73.0",
                "STL%": "8.2",
                "BLK%": "9.1",
                "TOV%": "6.3",
                "USG%": "100.0",
                "ORtg": "121.9",
                "DRtg": "69.1"
            }
        }
    }
]