[
    {
        "TEAM": "BOS",
        "HOME": false,
        "RECORD": "50-12",
        "STATS": {
            "BASIC": {
                "Starters": "Totals",
                "MP": "240",
                "FG": "37",
                "FGA": "78",
                "FG%": ".474",
                "3P": "9",
                "3PA": "23",
                "3P%": ".391",
                "FT": "17",
                "FTA": "21",
                "FT%": ".810",
                "ORB": "13",
                "DRB": "37",
                "TRB": "50",
                "AST": "24",
                "STL": "4",
                "BLK": "6",
                "TOV": "14",
                "PF": "30",
                "PTS": "100",
                "+/-": ""
            },
            "ADVANCE": {
                "Starters": "Totals",
                "MP": "240",
                "TS%": ".573",
                "eFG%": ".532",
                "3PAr": ".295",
                "FTr": ".269",
                "ORB%": "32.5",
                "DRB%": "60.7",
                "TRB%": "49.5",
                "AST%": "64.9",
                "STL%": "4.6",
                "BLK%": "7.7",
                "TOV%": "13.8",
                "USG%": "100.0",
                "ORtg": "114.4",
                "DRtg": "98.4"
            }
        }
    },
    {
        "TEAM": "PHI",
        "HOME": true,
        "RECORD": "30-34",
        "STATS": {
            "BASIC": {
                "Starters": "Totals",
                "MP": "240",
                "FG": "30",
                "FGA": "95",
                "FG%": ".316",
                "3P": "2",
                "3PA": "17",
                "3P%": ".118",
                "FT": "24",
                "FTA": "35",
                "FT%": ".686",
                "ORB": "24",
                "DRB": "27",
                "TRB": "51",
                "AST": "18",
                "STL": "7",
                "BLK": "7",
                "TOV": "7",
                "PF": "17",
                "PTS": "86",
                "+/-": ""
            },
            "ADVANCE": {
                "Starters": "Totals",
                "MP": "240",
                "TS%": ".389",
                "eFG%": ".326",
                "3PAr": ".179",
                "FTr": ".368",
                "ORB%": "39.3",
                "DRB%": "67.5",
                "TRB%": "50.5",
                "AST%": "60.0",
                "STL%": "8.0",
                "BLK%": "12.7",
                "TOV%": "6.0",
                "USG%": "100.0",
                "ORtg": "98.4",
                "DRtg": "114.4"
            }
        }
    }
]